bytedance_byted_traffic_shoot_api/__init__.py
bytedance_byted_traffic_shoot_api-0.0.1.dist-info/METADATA
bytedance_byted_traffic_shoot_api-0.0.1.dist-info/WHEEL
bytedance_byted_traffic_shoot_api-0.0.1.dist-info/top_level.txt
bytedance_byted_traffic_shoot_api-0.0.1.dist-info/RECORD
