Metadata-Version: 2.1
Name: bytedance-byted-traffic-shoot-api
Version: 0.0.1
Summary: A simple package named bytedance_byted_traffic_shoot_api
Home-page: https://github.com/artifact/bytedance_byted_traffic_shoot_api.git
Author: artifact
Author-email: artifact@example.com
License: UNKNOWN
Platform: UNKNOWN
Classifier: Programming Language :: Python :: 3
Classifier: License :: OSI Approved :: MIT License
Classifier: Operating System :: OS Independent
